aquiles_image-0.4.4.dist-info/licenses/LICENSE
aquilesimage/main.py
aquilesimage/cli/__init__.py
aquilesimage/cli/cli.py
aquilesimage/configs/__init__.py
aquilesimage/configs/configs.py
aquilesimage/models/__init__.py
aquilesimage/models/models.py
aquilesimage/pipelines/__init__.py
aquilesimage/pipelines/pipelines.py
aquilesimage/pipelines/video.py
aquilesimage/runtime/__init__.py
aquilesimage/runtime/batch_inf.py
aquilesimage/runtime/distributed_inference.py
aquilesimage/runtime/requestscopedpipeline.py
aquilesimage/runtime/scheduler.py
aquilesimage/runtime/worker_manager.py
aquilesimage/runtime/worker_process.py
aquilesimage/runtime/wrappers.py
aquilesimage/static/index.html
aquilesimage/utils/__init__.py
aquilesimage/utils/task.py
aquilesimage/utils/utils.py
aquilesimage/utils/utils_video.py
aquiles_image-0.4.4.dist-info/METADATA
aquiles_image-0.4.4.dist-info/WHEEL
aquiles_image-0.4.4.dist-info/entry_points.txt
aquiles_image-0.4.4.dist-info/top_level.txt
aquiles_image-0.4.4.dist-info/RECORD
