Metadata-Version: 2.4
Name: aquiles-image
Version: 0.4.4
Summary: A high-performance, memory-efficient inference server for diffusion models, compatible with the OpenAI client
Author-email: Aquiles-ai / Fredy <aquilesaicontact@gmail.com>
License: Apache License 2.0
Project-URL: Homepage, https://github.com/Aquiles-ai/Aquiles-Image
Project-URL: Issues, https://github.com/Aquiles-ai/Aquiles-Image/issues
Keywords: fastapi,ai
Classifier: Development Status :: 4 - Beta
Classifier: Programming Language :: Python :: 3
Classifier: Programming Language :: Python :: 3.8
Classifier: Programming Language :: Python :: 3.9
Classifier: Programming Language :: Python :: 3.10
Classifier: License :: OSI Approved :: Apache Software License
Classifier: Operating System :: OS Independent
Classifier: Environment :: Web Environment
Classifier: Topic :: Software Development :: Build Tools
Requires-Python: >=3.8
License-File: LICENSE
Requires-Dist: torch
Requires-Dist: torchvision
Requires-Dist: transformers
Requires-Dist: sentencepiece
Requires-Dist: fastapi
Requires-Dist: click>=8.0.0
Requires-Dist: uvicorn
Requires-Dist: ftfy
Requires-Dist: accelerate
Requires-Dist: xformers
Requires-Dist: protobuf
Requires-Dist: diffusers
Requires-Dist: platformdirs
Requires-Dist: aiofiles
Requires-Dist: python-multipart
Requires-Dist: openai
Requires-Dist: dm-tree
Requires-Dist: pymongo
Provides-Extra: dev
Requires-Dist: pytest; extra == "dev"
Requires-Dist: black; extra == "dev"
Requires-Dist: isort; extra == "dev"
Requires-Dist: mypy; extra == "dev"
Dynamic: license-file
